README.rst
setup.py
pyledger/__init__.py
pyledger/pyledger_message_pb2.py
pyledger/verify.py
pyledger.egg-info/PKG-INFO
pyledger.egg-info/SOURCES.txt
pyledger.egg-info/dependency_links.txt
pyledger.egg-info/entry_points.txt
pyledger.egg-info/requires.txt
pyledger.egg-info/top_level.txt