Metadata-Version: 1.1
Name: pyledger
Version: 0.5
Summary: A simple ledger for smart contracts written in Python
Home-page: UNKNOWN
Author: Guillem Borrell
Author-email: guillemborrell@gmail.com
License: UNKNOWN
Platform: UNKNOWN
Classifier: Development Status :: 3 - Alpha
Classifier: Environment :: Console
Classifier: Intended Audience :: Developers
Classifier: Programming Language :: Python
Classifier: Programming Language :: Python :: 3 :: Only
Classifier: Programming Language :: Python :: 3.5
Classifier: Programming Language :: Python :: 3.6
Classifier: License :: OSI Approved :: GNU Affero General Public License v3
